txtify/__about__.py
txtify/__init__.py
txtify/cli.py
txtify/converter.py
txtify-0.1.3.dist-info/METADATA
txtify-0.1.3.dist-info/WHEEL
txtify-0.1.3.dist-info/entry_points.txt
txtify-0.1.3.dist-info/licenses/LICENSE
txtify-0.1.3.dist-info/licenses/LICENSE.txt
txtify-0.1.3.dist-info/RECORD
