Metadata-Version: 2.4
Name: txtify
Version: 0.1.3
Summary: A versatile Python tool to convert documents (PPTX, DOCX, PDF, XLSX) to plain text, ideal for providing context to AI code assistants like GitHub Copilot and Amazon CodeWhisperer.
Author-email: Ray Rada <rayrada1@gmail.com>, Anthony Furst <anthony.furst@afs.com>
License-Expression: MIT
License-File: LICENSE
License-File: LICENSE.txt
Keywords: ai,code generation,context,converter,document,documentation,excel,github copilot,llm,pdf,powerpoint,text,word
Requires-Python: >=3.8
Requires-Dist: click
Requires-Dist: docx2txt
Requires-Dist: openpyxl
Requires-Dist: pandas
Requires-Dist: pypdf2
Requires-Dist: python-pptx
Requires-Dist: xlrd
